onchaindb/__init__.py
onchaindb/client.py
onchaindb/exceptions.py
onchaindb/types.py
onchaindb/http/__init__.py
onchaindb/http/client.py
onchaindb/http/interface.py
onchaindb/query/__init__.py
onchaindb/query/builder.py
onchaindb/query/condition_builder.py
onchaindb/query/field_condition.py
onchaindb/query/group_by_builder.py
onchaindb/query/join_builder.py
onchaindb/query/logical_operator.py
onchaindb/query/selection_builder.py
onchaindb/query/where_clause.py
onchaindb-0.2.1.dist-info/METADATA
onchaindb-0.2.1.dist-info/WHEEL
onchaindb-0.2.1.dist-info/RECORD
