Metadata-Version: 2.4
Name: onchaindb
Version: 0.2.1
Summary: Python SDK for OnChainDB - Decentralized database on Celestia
Project-URL: Homepage, https://onchaindb.io
Project-URL: Documentation, https://docs.onchaindb.io
Project-URL: Repository, https://github.com/onchaindb/sdk-python
Project-URL: Issues, https://github.com/onchaindb/sdk-python/issues
Author-email: OnChainDB Team <team@onchaindb.io>
License: MIT
Keywords: blockchain,celestia,database,decentralized,onchaindb
Classifier: Development Status :: 4 - Beta
Classifier: Intended Audience :: Developers
Classifier: License :: OSI Approved :: MIT License
Classifier: Programming Language :: Python :: 3
Classifier: Programming Language :: Python :: 3.9
Classifier: Programming Language :: Python :: 3.10
Classifier: Programming Language :: Python :: 3.11
Classifier: Programming Language :: Python :: 3.12
Classifier: Topic :: Database
Classifier: Topic :: Software Development :: Libraries :: Python Modules
Classifier: Typing :: Typed
Requires-Python: >=3.9
Requires-Dist: httpx>=0.25.0
Provides-Extra: dev
Requires-Dist: black>=23.0; extra == 'dev'
Requires-Dist: mypy>=1.0; extra == 'dev'
Requires-Dist: pytest-asyncio>=0.21; extra == 'dev'
Requires-Dist: pytest-cov>=4.0; extra == 'dev'
Requires-Dist: pytest>=7.0; extra == 'dev'
Requires-Dist: respx>=0.20; extra == 'dev'
Requires-Dist: ruff>=0.1; extra == 'dev'
